{
    "schemes": [
        "http"
    ],
    "swagger": "2.0",
    "info": {
        "description": "API для управления квантовыми задачами и гейтами",
        "title": "Quantum Tasks API",
        "termsOfService": "http://swagger.io/terms/",
        "contact": {
            "name": "API Support",
            "url": "http://www.swagger.io/support",
            "email": "support@swagger.io"
        },
        "license": {
            "name": "MIT",
            "url": "https://opensource.org/licenses/MIT"
        },
        "version": "1.0"
    },
    "host": "localhost:8080",
    "basePath": "/",
    "paths": {
        "/api/auth/logout": {
            "post": {
                "security": [
                    {
                        "BearerAuth": []
                    }
                ],
                "description": "Добавляет JWT токен в черный список и выполняет деавторизацию",
                "consumes": [
                    "application/json"
                ],
                "produces": [
                    "application/json"
                ],
                "tags": [
                    "Users"
                ],
                "summary": "Выход из системы",
                "responses": {
                    "200": {
                        "description": "Сообщение об успешном выходе\" {\"message\": \"Деавторизация прошла успешно\"}",
                        "schema": {
                            "type": "object"
                        }
                    },
                    "400": {
                        "description": "Invalid authorization header",
                        "schema": {
                            "type": "string"
                        }
                    },
                    "500": {
                        "description": "Internal server error",
                        "schema": {
                            "type": "string"
                        }
                    }
                }
            }
        },
        "/api/draft/gates/{id}": {
            "post": {
                "description": "Добавляет указанный гейт в текущую черновую задачу пользователя.",
                "produces": [
                    "application/json"
                ],
                "tags": [
                    "Gates"
                ],
                "summary": "Добавить гейт в черновик задачи",
                "parameters": [
                    {
                        "type": "integer",
                        "description": "ID гейта",
                        "name": "id",
                        "in": "path",
                        "required": true
                    }
                ],
                "responses": {
                    "201": {
                        "description": "Created",
                        "schema": {
                            "$ref": "#/definitions/internal_app_handler.DTO_Resp_TaskServiceLink"
                        }
                    },
                    "400": {
                        "description": "Некорректный ID гейта",
                        "schema": {
                            "type": "object",
                            "additionalProperties": {
                                "type": "string"
                            }
                        }
                    },
                    "401": {
                        "description": "Требуется авторизация",
                        "schema": {
                            "type": "object",
                            "additionalProperties": {
                                "type": "string"
                            }
                        }
                    },
                    "500": {
                        "description": "Ошибка при добавлении гейта в задачу",
                        "schema": {
                            "type": "object",
                            "additionalProperties": {
                                "type": "string"
                            }
                        }
                    }
                }
            }
        },
        "/api/gates": {
            "get": {
                "description": "Возвращает список всех гейтов. Поддерживает фильтрацию по названию.",
                "produces": [
                    "application/json"
                ],
                "tags": [
                    "Gates"
                ],
                "summary": "Получить список гейтов",
                "parameters": [
                    {
                        "type": "string",
                        "description": "Фильтр по названию гейта (поиск по подстроке)",
                        "name": "title",
                        "in": "query"
                    }
                ],
                "responses": {
                    "200": {
                        "description": "OK",
                        "schema": {
                            "type": "array",
                            "items": {
                                "$ref": "#/definitions/internal_app_handler.DTO_Resp_Gate"
                            }
                        }
                    },
                    "500": {
                        "description": "Внутренняя ошибка сервера",
                        "schema": {
                            "type": "object",
                            "additionalProperties": {
                                "type": "string"
                            }
                        }
                    }
                }
            },
            "post": {
                "description": "Создаёт новый квантовый гейт с указанными параметрами.",
                "consumes": [
                    "application/json"
                ],
                "produces": [
                    "application/json"
                ],
                "tags": [
                    "Gates"
                ],
                "summary": "Создать новый гейт",
                "parameters": [
                    {
                        "description": "Данные нового гейта",
                        "name": "gate",
                        "in": "body",
                        "required": true,
                        "schema": {
                            "$ref": "#/definitions/internal_app_handler.DTO_Req_GateCreate"
                        }
                    }
                ],
                "responses": {
                    "201": {
                        "description": "Created",
                        "schema": {
                            "$ref": "#/definitions/front_start_internal_app_ds.Gate"
                        }
                    },
                    "400": {
                        "description": "Некорректные данные запроса",
                        "schema": {
                            "type": "object",
                            "additionalProperties": {
                                "type": "string"
                            }
                        }
                    },
                    "500": {
                        "description": "Ошибка при создании гейта",
                        "schema": {
                            "type": "object",
                            "additionalProperties": {
                                "type": "string"
                            }
                        }
                    }
                }
            }
        },
        "/api/gates/{id}": {
            "get": {
                "description": "Возвращает полную информацию о гейте по его идентификатору.",
                "produces": [
                    "application/json"
                ],
                "tags": [
                    "Gates"
                ],
                "summary": "Получить гейт по ID",
                "parameters": [
                    {
                        "type": "integer",
                        "description": "ID гейта",
                        "name": "id",
                        "in": "path",
                        "required": true
                    }
                ],
                "responses": {
                    "200": {
                        "description": "OK",
                        "schema": {
                            "$ref": "#/definitions/front_start_internal_app_ds.Gate"
                        }
                    },
                    "400": {
                        "description": "Некорректный ID",
                        "schema": {
                            "type": "object",
                            "additionalProperties": {
                                "type": "string"
                            }
                        }
                    },
                    "404": {
                        "description": "Гейт не найден",
                        "schema": {
                            "type": "object",
                            "additionalProperties": {
                                "type": "string"
                            }
                        }
                    },
                    "500": {
                        "description": "Внутренняя ошибка сервера",
                        "schema": {
                            "type": "object",
                            "additionalProperties": {
                                "type": "string"
                            }
                        }
                    }
                }
            },
            "put": {
                "description": "Обновляет существующий гейт по ID.",
                "consumes": [
                    "application/json"
                ],
                "produces": [
                    "application/json"
                ],
                "tags": [
                    "Gates"
                ],
                "summary": "Обновить гейт",
                "parameters": [
                    {
                        "type": "integer",
                        "description": "ID гейта",
                        "name": "id",
                        "in": "path",
                        "required": true
                    },
                    {
                        "description": "Обновлённые данные гейта",
                        "name": "gate",
                        "in": "body",
                        "required": true,
                        "schema": {
                            "$ref": "#/definitions/internal_app_handler.DTO_Req_GateCreate"
                        }
                    }
                ],
                "responses": {
                    "200": {
                        "description": "OK",
                        "schema": {
                            "$ref": "#/definitions/front_start_internal_app_ds.Gate"
                        }
                    },
                    "400": {
                        "description": "Некорректные данные запроса или ID",
                        "schema": {
                            "type": "object",
                            "additionalProperties": {
                                "type": "string"
                            }
                        }
                    },
                    "500": {
                        "description": "Ошибка при обновлении гейта",
                        "schema": {
                            "type": "object",
                            "additionalProperties": {
                                "type": "string"
                            }
                        }
                    }
                }
            },
            "delete": {
                "description": "Удаляет гейт по ID.",
                "produces": [
                    "application/json"
                ],
                "tags": [
                    "Gates"
                ],
                "summary": "Удалить гейт",
                "parameters": [
                    {
                        "type": "integer",
                        "description": "ID гейта",
                        "name": "id",
                        "in": "path",
                        "required": true
                    }
                ],
                "responses": {
                    "200": {
                        "description": "OK",
                        "schema": {
                            "$ref": "#/definitions/internal_app_handler.DTO_Resp_SimpleID"
                        }
                    },
                    "400": {
                        "description": "Некорректный ID",
                        "schema": {
                            "type": "object",
                            "additionalProperties": {
                                "type": "string"
                            }
                        }
                    },
                    "500": {
                        "description": "Ошибка при удалении гейта",
                        "schema": {
                            "type": "object",
                            "additionalProperties": {
                                "type": "string"
                            }
                        }
                    }
                }
            }
        },
        "/api/gates/{id}/image": {
            "post": {
                "description": "Загружает изображение гейта и обновляет URL в базе данных.",
                "consumes": [
                    "multipart/form-data"
                ],
                "produces": [
                    "application/json"
                ],
                "tags": [
                    "Gates"
                ],
                "summary": "Загрузить изображение для гейта",
                "parameters": [
                    {
                        "type": "integer",
                        "description": "ID гейта",
                        "name": "id",
                        "in": "path",
                        "required": true
                    },
                    {
                        "type": "file",
                        "description": "Изображение гейта",
                        "name": "file",
                        "in": "formData",
                        "required": true
                    }
                ],
                "responses": {
                    "201": {
                        "description": "Created",
                        "schema": {
                            "$ref": "#/definitions/internal_app_handler.DTO_Resp_UploadImg"
                        }
                    },
                    "400": {
                        "description": "Некорректный ID или отсутствует файл",
                        "schema": {
                            "type": "object",
                            "additionalProperties": {
                                "type": "string"
                            }
                        }
                    },
                    "500": {
                        "description": "Ошибка при загрузке изображения",
                        "schema": {
                            "type": "object",
                            "additionalProperties": {
                                "type": "string"
                            }
                        }
                    }
                }
            }
        },
        "/api/quantum_task/current": {
            "get": {
                "description": "Возвращает ID текущей черновой задачи и количество добавленных в неё гейтов.",
                "produces": [
                    "application/json"
                ],
                "tags": [
                    "QuantumTasks"
                ],
                "summary": "Получить информацию о текущей черновой задаче",
                "responses": {
                    "200": {
                        "description": "OK",
                        "schema": {
                            "$ref": "#/definitions/internal_app_handler.DTO_Resp_CurrTaskInfo"
                        }
                    },
                    "500": {
                        "description": "Ошибка при получении данных задачи",
                        "schema": {
                            "type": "object",
                            "additionalProperties": {
                                "type": "string"
                            }
                        }
                    }
                }
            }
        },
        "/api/quantum_tasks": {
            "get": {
                "security": [
                    {
                        "BearerAuth": []
                    }
                ],
                "description": "Возвращает список квантовых задач. Пользователь видит только свои задачи, модератор - все задачи, неавторизованный пользователь - ошибку доступа.",
                "consumes": [
                    "application/json"
                ],
                "produces": [
                    "application/json"
                ],
                "tags": [
                    "QuantumTasks"
                ],
                "summary": "Получить список задач",
                "parameters": [
                    {
                        "type": "string",
                        "description": "Фильтр по статусу",
                        "name": "status",
                        "in": "query"
                    },
                    {
                        "type": "string",
                        "description": "Начальная дата (фильтр от)",
                        "name": "from",
                        "in": "query"
                    },
                    {
                        "type": "string",
                        "description": "Конечная дата (фильтр до)",
                        "name": "to",
                        "in": "query"
                    }
                ],
                "responses": {
                    "200": {
                        "description": "Список задач",
                        "schema": {
                            "type": "array",
                            "items": {
                                "$ref": "#/definitions/internal_app_handler.DTO_Resp_Tasks"
                            }
                        }
                    },
                    "401": {
                        "description": "Unauthorized",
                        "schema": {
                            "type": "string"
                        }
                    },
                    "403": {
                        "description": "Forbidden",
                        "schema": {
                            "type": "string"
                        }
                    },
                    "500": {
                        "description": "Internal server error",
                        "schema": {
                            "type": "string"
                        }
                    }
                }
            }
        },
        "/api/quantum_tasks/{id}": {
            "get": {
                "description": "Возвращает детальную информацию о квантовой задаче по её идентификатору",
                "consumes": [
                    "application/json"
                ],
                "produces": [
                    "application/json"
                ],
                "tags": [
                    "QuantumTasks"
                ],
                "summary": "Получить задачу по ID",
                "parameters": [
                    {
                        "type": "integer",
                        "description": "ID задачи",
                        "name": "id",
                        "in": "path",
                        "required": true
                    }
                ],
                "responses": {
                    "200": {
                        "description": "Детали задачи",
                        "schema": {
                            "$ref": "#/definitions/internal_app_handler.DTO_Resp_Tasks"
                        }
                    },
                    "400": {
                        "description": "Invalid task ID",
                        "schema": {
                            "type": "string"
                        }
                    },
                    "404": {
                        "description": "Task not found",
                        "schema": {
                            "type": "string"
                        }
                    }
                }
            },
            "put": {
                "description": "Обновляет описание квантовой задачи",
                "consumes": [
                    "application/json"
                ],
                "produces": [
                    "application/json"
                ],
                "tags": [
                    "QuantumTasks"
                ],
                "summary": "Обновить задачу",
                "parameters": [
                    {
                        "type": "integer",
                        "description": "ID задачи",
                        "name": "id",
                        "in": "path",
                        "required": true
                    },
                    {
                        "description": "Данные для обновления",
                        "name": "request",
                        "in": "body",
                        "required": true,
                        "schema": {
                            "$ref": "#/definitions/internal_app_handler.DTO_Req_TaskUpd"
                        }
                    }
                ],
                "responses": {
                    "200": {
                        "description": "Обновленная задача",
                        "schema": {
                            "$ref": "#/definitions/internal_app_handler.DTO_Resp_Tasks"
                        }
                    },
                    "400": {
                        "description": "Invalid input",
                        "schema": {
                            "type": "string"
                        }
                    },
                    "500": {
                        "description": "Internal server error",
                        "schema": {
                            "type": "string"
                        }
                    }
                }
            },
            "delete": {
                "description": "Полностью удаляет квантовую задачу из системы",
                "consumes": [
                    "application/json"
                ],
                "produces": [
                    "application/json"
                ],
                "tags": [
                    "QuantumTasks"
                ],
                "summary": "Удалить задачу",
                "parameters": [
                    {
                        "type": "integer",
                        "description": "ID задачи",
                        "name": "id",
                        "in": "path",
                        "required": true
                    }
                ],
                "responses": {
                    "200": {
                        "description": "ID удаленной задачи",
                        "schema": {
                            "$ref": "#/definitions/internal_app_handler.DTO_Resp_SimpleID"
                        }
                    },
                    "400": {
                        "description": "Invalid task ID",
                        "schema": {
                            "type": "string"
                        }
                    },
                    "500": {
                        "description": "Internal server error",
                        "schema": {
                            "type": "string"
                        }
                    }
                }
            }
        },
        "/api/quantum_tasks/{id}/form": {
            "put": {
                "description": "Переводит задачу из статуса черновика в статус сформированной",
                "consumes": [
                    "application/json"
                ],
                "produces": [
                    "application/json"
                ],
                "tags": [
                    "QuantumTasks"
                ],
                "summary": "Сформировать задачу",
                "parameters": [
                    {
                        "type": "integer",
                        "description": "ID задачи",
                        "name": "id",
                        "in": "path",
                        "required": true
                    }
                ],
                "responses": {
                    "200": {
                        "description": "Сформированная задача",
                        "schema": {
                            "$ref": "#/definitions/internal_app_handler.DTO_Resp_Tasks"
                        }
                    },
                    "400": {
                        "description": "Invalid task ID or cannot form task",
                        "schema": {
                            "type": "string"
                        }
                    }
                }
            }
        },
        "/api/quantum_tasks/{id}/resolve": {
            "put": {
                "description": "Выполняет завершение или отклонение квантовой задачи с вычислением результата",
                "consumes": [
                    "application/json"
                ],
                "produces": [
                    "application/json"
                ],
                "tags": [
                    "QuantumTasks"
                ],
                "summary": "Завершить/отклонить задачу",
                "parameters": [
                    {
                        "type": "integer",
                        "description": "ID задачи",
                        "name": "id",
                        "in": "path",
                        "required": true
                    },
                    {
                        "description": "Действие с задачей",
                        "name": "request",
                        "in": "body",
                        "required": true,
                        "schema": {
                            "$ref": "#/definitions/internal_app_handler.DTO_Req_TaskResolve"
                        }
                    }
                ],
                "responses": {
                    "200": {
                        "description": "Решенная задача",
                        "schema": {
                            "$ref": "#/definitions/internal_app_handler.DTO_Resp_Tasks"
                        }
                    },
                    "400": {
                        "description": "Invalid input or missing required fields",
                        "schema": {
                            "type": "string"
                        }
                    },
                    "401": {
                        "description": "Unauthorized",
                        "schema": {
                            "type": "string"
                        }
                    },
                    "404": {
                        "description": "Task not found",
                        "schema": {
                            "type": "string"
                        }
                    },
                    "500": {
                        "description": "Internal server error",
                        "schema": {
                            "type": "string"
                        }
                    }
                }
            }
        },
        "/api/tasks/{task_id}/services/{service_id}": {
            "put": {
                "description": "Обновляет значение градусов для конкретного гейта в задаче",
                "consumes": [
                    "application/json"
                ],
                "produces": [
                    "application/json"
                ],
                "tags": [
                    "M-M"
                ],
                "summary": "Обновить градусы гейта",
                "parameters": [
                    {
                        "type": "integer",
                        "description": "ID задачи",
                        "name": "task_id",
                        "in": "path",
                        "required": true
                    },
                    {
                        "type": "integer",
                        "description": "ID гейта",
                        "name": "service_id",
                        "in": "path",
                        "required": true
                    },
                    {
                        "description": "Новые значения градусов",
                        "name": "request",
                        "in": "body",
                        "required": true,
                        "schema": {
                            "$ref": "#/definitions/internal_app_handler.DTO_Req_DegreesUpd"
                        }
                    }
                ],
                "responses": {
                    "200": {
                        "description": "Обновленные данные",
                        "schema": {
                            "$ref": "#/definitions/internal_app_handler.DTO_Resp_UpdateDegrees"
                        }
                    },
                    "400": {
                        "description": "Invalid input",
                        "schema": {
                            "type": "string"
                        }
                    },
                    "500": {
                        "description": "Internal server error",
                        "schema": {
                            "type": "string"
                        }
                    }
                }
            },
            "delete": {
                "description": "Удаляет связь между гейтом и задачей",
                "consumes": [
                    "application/json"
                ],
                "produces": [
                    "application/json"
                ],
                "tags": [
                    "M-M"
                ],
                "summary": "Удалить гейт из задачи",
                "parameters": [
                    {
                        "type": "integer",
                        "description": "ID задачи",
                        "name": "task_id",
                        "in": "path",
                        "required": true
                    },
                    {
                        "type": "integer",
                        "description": "ID гейта",
                        "name": "service_id",
                        "in": "path",
                        "required": true
                    }
                ],
                "responses": {
                    "200": {
                        "description": "Информация об удаленной связи",
                        "schema": {
                            "$ref": "#/definitions/internal_app_handler.DTO_Resp_TaskServiceLink"
                        }
                    },
                    "400": {
                        "description": "Invalid IDs",
                        "schema": {
                            "type": "string"
                        }
                    },
                    "500": {
                        "description": "Internal server error",
                        "schema": {
                            "type": "string"
                        }
                    }
                }
            }
        },
        "/api/users/me": {
            "get": {
                "security": [
                    {
                        "BearerAuth": []
                    }
                ],
                "description": "Возвращает данные аутентифицированного пользователя",
                "consumes": [
                    "application/json"
                ],
                "produces": [
                    "application/json"
                ],
                "tags": [
                    "Users"
                ],
                "summary": "Получить текущего пользователя",
                "responses": {
                    "200": {
                        "description": "Данные пользователя",
                        "schema": {
                            "$ref": "#/definitions/internal_app_handler.DTO_Resp_User"
                        }
                    },
                    "401": {
                        "description": "Unauthorized",
                        "schema": {
                            "type": "string"
                        }
                    },
                    "500": {
                        "description": "Internal server error",
                        "schema": {
                            "type": "string"
                        }
                    }
                }
            },
            "put": {
                "security": [
                    {
                        "BearerAuth": []
                    }
                ],
                "description": "Обновляет пароль текущего аутентифицированного пользователя",
                "consumes": [
                    "application/json"
                ],
                "produces": [
                    "application/json"
                ],
                "tags": [
                    "Users"
                ],
                "summary": "Обновить данные пользователя",
                "parameters": [
                    {
                        "description": "Новые данные пользователя",
                        "name": "request",
                        "in": "body",
                        "required": true,
                        "schema": {
                            "$ref": "#/definitions/internal_app_handler.DTO_Req_UserUpd"
                        }
                    }
                ],
                "responses": {
                    "200": {
                        "description": "Обновленные данные пользователя",
                        "schema": {
                            "$ref": "#/definitions/internal_app_handler.DTO_Resp_User"
                        }
                    },
                    "400": {
                        "description": "Invalid input data",
                        "schema": {
                            "type": "string"
                        }
                    },
                    "401": {
                        "description": "Unauthorized",
                        "schema": {
                            "type": "string"
                        }
                    },
                    "500": {
                        "description": "Internal server error",
                        "schema": {
                            "type": "string"
                        }
                    }
                }
            }
        },
        "/login": {
            "post": {
                "description": "Выполняет вход пользователя и возвращает JWT токен",
                "consumes": [
                    "application/json"
                ],
                "produces": [
                    "application/json"
                ],
                "tags": [
                    "Users"
                ],
                "summary": "Аутентификация пользователя",
                "parameters": [
                    {
                        "description": "Учетные данные",
                        "name": "request",
                        "in": "body",
                        "required": true,
                        "schema": {
                            "$ref": "#/definitions/internal_app_handler.DTO_Req_UserReg"
                        }
                    }
                ],
                "responses": {
                    "200": {
                        "description": "Токен и данные пользователя",
                        "schema": {
                            "$ref": "#/definitions/internal_app_handler.DTO_Resp_TokenLogin"
                        }
                    },
                    "400": {
                        "description": "Invalid input data",
                        "schema": {
                            "type": "string"
                        }
                    },
                    "401": {
                        "description": "Invalid credentials",
                        "schema": {
                            "type": "string"
                        }
                    },
                    "500": {
                        "description": "Internal server error",
                        "schema": {
                            "type": "string"
                        }
                    }
                }
            }
        },
        "/users": {
            "post": {
                "description": "Создает нового пользователя с указанными логином и паролем",
                "consumes": [
                    "application/json"
                ],
                "produces": [
                    "application/json"
                ],
                "tags": [
                    "Users"
                ],
                "summary": "Регистрация пользователя",
                "parameters": [
                    {
                        "description": "Данные для регистрации",
                        "name": "request",
                        "in": "body",
                        "required": true,
                        "schema": {
                            "$ref": "#/definitions/internal_app_handler.DTO_Req_UserReg"
                        }
                    }
                ],
                "responses": {
                    "200": {
                        "description": "Зарегистрированный пользователь",
                        "schema": {
                            "$ref": "#/definitions/internal_app_handler.DTO_Resp_User"
                        }
                    },
                    "400": {
                        "description": "Invalid input data",
                        "schema": {
                            "type": "string"
                        }
                    },
                    "500": {
                        "description": "Internal server error",
                        "schema": {
                            "type": "string"
                        }
                    }
                }
            }
        }
    },
    "definitions": {
        "front_start_internal_app_ds.DegreesToGates": {
            "type": "object",
            "properties": {
                "degrees": {
                    "type": "number",
                    "format": "float32"
                },
                "gate": {
                    "description": "Связи, необходимые для работы сервиса",
                    "allOf": [
                        {
                            "$ref": "#/definitions/front_start_internal_app_ds.Gate"
                        }
                    ]
                },
                "id_gate": {
                    "type": "integer"
                },
                "id_task": {
                    "type": "integer"
                },
                "task": {
                    "$ref": "#/definitions/front_start_internal_app_ds.QuantumTask"
                }
            }
        },
        "front_start_internal_app_ds.Gate": {
            "type": "object",
            "properties": {
                "degrees": {
                    "description": "Несущая связь",
                    "type": "array",
                    "items": {
                        "$ref": "#/definitions/front_start_internal_app_ds.DegreesToGates"
                    }
                },
                "description": {
                    "type": "string"
                },
                "fullInfo": {
                    "description": "subject area",
                    "type": "string"
                },
                "i0j0": {
                    "type": "integer"
                },
                "i0j1": {
                    "type": "integer"
                },
                "i1j0": {
                    "type": "integer"
                },
                "i1j1": {
                    "type": "integer"
                },
                "id_gate": {
                    "type": "integer"
                },
                "image": {
                    "type": "string"
                },
                "matrix_koeff": {
                    "type": "number"
                },
                "status": {
                    "type": "boolean"
                },
                "theAxis": {
                    "type": "string"
                },
                "title": {
                    "type": "string"
                }
            }
        },
        "front_start_internal_app_ds.QuantumTask": {
            "type": "object",
            "properties": {
                "conclusionDate": {
                    "type": "string"
                },
                "creationDate": {
                    "type": "string"
                },
                "formedDate": {
                    "type": "string"
                },
                "gatesDegrees": {
                    "description": "Несущая связь",
                    "type": "array",
                    "items": {
                        "$ref": "#/definitions/front_start_internal_app_ds.DegreesToGates"
                    }
                },
                "id_moderator": {
                    "type": "integer"
                },
                "id_task": {
                    "type": "integer"
                },
                "id_user": {
                    "type": "integer"
                },
                "moderator": {
                    "$ref": "#/definitions/front_start_internal_app_ds.Users"
                },
                "res_koeff_0": {
                    "type": "number"
                },
                "res_koeff_1": {
                    "type": "number"
                },
                "taskDescription": {
                    "description": "Задание пользователя",
                    "type": "string"
                },
                "taskStatus": {
                    "type": "string"
                },
                "user": {
                    "description": "Связь для программы",
                    "allOf": [
                        {
                            "$ref": "#/definitions/front_start_internal_app_ds.Users"
                        }
                    ]
                }
            }
        },
        "front_start_internal_app_ds.Users": {
            "type": "object",
            "properties": {
                "id_user": {
                    "type": "integer"
                },
                "isAdmin": {
                    "type": "boolean"
                },
                "login": {
                    "type": "string"
                },
                "password": {
                    "type": "string"
                }
            }
        },
        "internal_app_handler.DTO_Req_DegreesUpd": {
            "description": "Данные для обновления углов поворота гейта",
            "type": "object",
            "required": [
                "degrees"
            ],
            "properties": {
                "degrees": {
                    "type": "number",
                    "example": 45.5
                }
            }
        },
        "internal_app_handler.DTO_Req_GateCreate": {
            "description": "Данные для создания нового квантового гейта",
            "type": "object",
            "required": [
                "title"
            ],
            "properties": {
                "description": {
                    "type": "string",
                    "example": "Quantum Fourier transform gate"
                },
                "full_info": {
                    "type": "string",
                    "example": "Creates superposition states"
                },
                "i0j0": {
                    "type": "integer",
                    "example": 1
                },
                "i0j1": {
                    "type": "integer",
                    "example": 0
                },
                "i1j0": {
                    "type": "integer",
                    "example": 0
                },
                "i1j1": {
                    "type": "integer",
                    "example": 1
                },
                "matrix_koeff": {
                    "type": "number",
                    "example": 0.707
                },
                "status": {
                    "type": "boolean",
                    "example": true
                },
                "the_axis": {
                    "type": "string",
                    "enum": [
                        "X",
                        "Y",
                        "Z",
                        "non"
                    ],
                    "example": "X"
                },
                "title": {
                    "type": "string",
                    "example": "Hadamard Gate"
                }
            }
        },
        "internal_app_handler.DTO_Req_TaskResolve": {
            "description": "Данные для завершения или отклонения квантовой задачи",
            "type": "object",
            "required": [
                "action"
            ],
            "properties": {
                "action": {
                    "type": "string",
                    "enum": [
                        "complete",
                        "reject"
                    ],
                    "example": "complete"
                }
            }
        },
        "internal_app_handler.DTO_Req_TaskUpd": {
            "description": "Данные для обновления описания квантовой задачи",
            "type": "object",
            "required": [
                "task_description"
            ],
            "properties": {
                "task_description": {
                    "type": "string",
                    "example": "Calculate quantum state probabilities"
                }
            }
        },
        "internal_app_handler.DTO_Req_UserReg": {
            "description": "Данные для регистрации нового пользователя",
            "type": "object",
            "required": [
                "login",
                "password"
            ],
            "properties": {
                "login": {
                    "type": "string",
                    "example": "quantum_user"
                },
                "password": {
                    "type": "string",
                    "example": "secure_password_123"
                }
            }
        },
        "internal_app_handler.DTO_Req_UserUpd": {
            "description": "Данные для обновления пароля пользователя",
            "type": "object",
            "properties": {
                "password": {
                    "type": "string",
                    "example": "new_secure_password"
                }
            }
        },
        "internal_app_handler.DTO_Resp_CurrTaskInfo": {
            "description": "Статистика по текущей задаче пользователя",
            "type": "object",
            "properties": {
                "services_count": {
                    "type": "integer",
                    "example": 3
                },
                "task_id": {
                    "type": "integer",
                    "example": 5
                }
            }
        },
        "internal_app_handler.DTO_Resp_Gate": {
            "description": "Полная информация о квантовом гейте",
            "type": "object",
            "properties": {
                "description": {
                    "type": "string",
                    "example": "Quantum NOT gate"
                },
                "full_info": {
                    "type": "string",
                    "example": "Bit flip gate"
                },
                "i0j0": {
                    "type": "integer",
                    "example": 0
                },
                "i0j1": {
                    "type": "integer",
                    "example": 1
                },
                "i1j0": {
                    "type": "integer",
                    "example": 1
                },
                "i1j1": {
                    "type": "integer",
                    "example": 0
                },
                "id_gate": {
                    "type": "integer",
                    "example": 1
                },
                "image": {
                    "type": "string",
                    "example": "gate_x.png"
                },
                "matrix_koeff": {
                    "type": "number",
                    "example": 1
                },
                "status": {
                    "type": "boolean",
                    "example": true
                },
                "the_axis": {
                    "type": "string",
                    "example": "X"
                },
                "title": {
                    "type": "string",
                    "example": "Pauli-X"
                }
            }
        },
        "internal_app_handler.DTO_Resp_GatesDegrees": {
            "description": "Информация о гейте в задаче с указанными углами поворота",
            "type": "object",
            "properties": {
                "degrees": {
                    "type": "number",
                    "example": 90
                },
                "id_gate": {
                    "type": "integer",
                    "example": 2
                },
                "id_task": {
                    "type": "integer",
                    "example": 1
                }
            }
        },
        "internal_app_handler.DTO_Resp_SimpleID": {
            "type": "object",
            "properties": {
                "id": {
                    "type": "integer",
                    "example": 1
                }
            }
        },
        "internal_app_handler.DTO_Resp_TaskServiceLink": {
            "description": "Информация о связи между задачей и гейтом",
            "type": "object",
            "properties": {
                "service_id": {
                    "type": "integer",
                    "example": 3
                },
                "task_id": {
                    "type": "integer",
                    "example": 1
                }
            }
        },
        "internal_app_handler.DTO_Resp_Tasks": {
            "description": "Полная информация о квантовой задаче включая гейты",
            "type": "object",
            "properties": {
                "conclusion_date": {
                    "type": "string",
                    "example": "2023-10-01T16:04:05Z"
                },
                "creation_date": {
                    "type": "string",
                    "example": "2023-10-01T15:04:05Z"
                },
                "gates_degrees": {
                    "type": "array",
                    "items": {
                        "$ref": "#/definitions/internal_app_handler.DTO_Resp_GatesDegrees"
                    }
                },
                "id_task": {
                    "type": "integer",
                    "example": 1
                },
                "id_user": {
                    "type": "integer",
                    "example": 1
                },
                "res_koeff_0": {
                    "type": "number",
                    "example": 0.707
                },
                "res_koeff_1": {
                    "type": "number",
                    "example": 0.707
                },
                "task_description": {
                    "type": "string",
                    "example": "Quantum state calculation"
                },
                "task_status": {
                    "type": "string",
                    "enum": [
                        "draft",
                        "formed",
                        "completed",
                        "rejected"
                    ],
                    "example": "completed"
                }
            }
        },
        "internal_app_handler.DTO_Resp_TokenLogin": {
            "description": "Ответ содержащий JWT токен и данные пользователя",
            "type": "object",
            "properties": {
                "token": {
                    "type": "string",
                    "example": "eyJhbGciOiJIUzI1NiIsInR5cCI6IkpXVCJ9..."
                },
                "user": {
                    "$ref": "#/definitions/internal_app_handler.DTO_User"
                }
            }
        },
        "internal_app_handler.DTO_Resp_UpdateDegrees": {
            "description": "Результат обновления углов поворота гейта",
            "type": "object",
            "properties": {
                "degrees": {
                    "type": "number",
                    "example": 45.5
                },
                "service_id": {
                    "type": "integer",
                    "example": 2
                },
                "task_id": {
                    "type": "integer",
                    "example": 1
                }
            }
        },
        "internal_app_handler.DTO_Resp_UploadImg": {
            "description": "Результат загрузки изображения для гейта",
            "type": "object",
            "properties": {
                "id": {
                    "type": "integer",
                    "example": 1
                },
                "image": {
                    "type": "string",
                    "example": "gate_image.png"
                }
            }
        },
        "internal_app_handler.DTO_Resp_User": {
            "description": "Упрощенные данные пользователя",
            "type": "object",
            "properties": {
                "login": {
                    "type": "string",
                    "example": "quantum_researcher"
                }
            }
        },
        "internal_app_handler.DTO_User": {
            "description": "Базовая информация о пользователе системы",
            "type": "object",
            "properties": {
                "id_user": {
                    "type": "integer",
                    "example": 1
                },
                "is_admin": {
                    "type": "boolean",
                    "example": false
                },
                "login": {
                    "type": "string",
                    "example": "quantum_researcher"
                }
            }
        }
    },
    "securityDefinitions": {
        "BearerAuth": {
            "description": "JWT токен в формате: \"Bearer {token}\"",
            "type": "apiKey",
            "name": "Authorization",
            "in": "header"
        }
    }
}